soundy/Notes.py
soundy/__init__.py
soundy/__main__.py
soundy/setup.py
soundy/soundy.py
soundy/test.py
soundy-1.0.2.dist-info/METADATA
soundy-1.0.2.dist-info/WHEEL
soundy-1.0.2.dist-info/top_level.txt
soundy-1.0.2.dist-info/RECORD
